README.md
setup.py
matillion_columns/__init__.py
matillion_columns/command_line.py
matillion_columns.egg-info/PKG-INFO
matillion_columns.egg-info/SOURCES.txt
matillion_columns.egg-info/dependency_links.txt
matillion_columns.egg-info/entry_points.txt
matillion_columns.egg-info/requires.txt
matillion_columns.egg-info/top_level.txt