Metadata-Version: 2.1
Name: matillion-columns
Version: 0.0.3
Summary: A tool to generate columns in our Matillion grid variables using CSVs on S3
Home-page: https://github.com/cjdinsmore/matillion_columns
Author: Caleb Dinsmore
Author-email: caleb.dinsmore@edusource.us
License: MIT
Platform: UNKNOWN
Classifier: Programming Language :: Python :: 3
Classifier: License :: OSI Approved :: MIT License
Classifier: Operating System :: OS Independent
